README.md
setup.cfg
setup.py
mlnd_distributions_sup/Binomialdistribution.py
mlnd_distributions_sup/Gaussiandistribution.py
mlnd_distributions_sup/Generaldistribution.py
mlnd_distributions_sup/__init__.py
mlnd_distributions_sup.egg-info/PKG-INFO
mlnd_distributions_sup.egg-info/SOURCES.txt
mlnd_distributions_sup.egg-info/dependency_links.txt
mlnd_distributions_sup.egg-info/not-zip-safe
mlnd_distributions_sup.egg-info/top_level.txt