Metadata-Version: 1.0
Name: mlnd-distributions-sup
Version: 0.1
Summary: Gaussian and Binomial Distributions
Home-page: UNKNOWN
Author: Supreeth Sreekanth
Author-email: UNKNOWN
License: UNKNOWN
Platform: UNKNOWN
